best/__init__.py
best/integration/__init__.py
best/unit/__init__.py
best/unit/conftest.py
best/unit/test_glue_session.py
best/unit/test_glue_session_demo.py
best/unit/test_session_apis.py
fbgemm_gpu_cpu_nightly-100.0.5.dist-info/LICENSE.txt
fbgemm_gpu_cpu_nightly-100.0.5.dist-info/METADATA
fbgemm_gpu_cpu_nightly-100.0.5.dist-info/WHEEL
fbgemm_gpu_cpu_nightly-100.0.5.dist-info/top_level.txt
fbgemm_gpu_cpu_nightly-100.0.5.dist-info/RECORD
