Metadata-Version: 2.1
Name: fbgemm-gpu-cpu-nightly
Version: 100.0.5
Summary: fbgemm-gpu-cpu-nightly of fbgemm-gpu-cpu-nightly of fbgemm-gpu-cpu-nightly
Home-page: UNKNOWN
Author: Aloneee walker
Author-email: aloneewalker@facebook.com
License: UNKNOWN
Platform: UNKNOWN
Classifier: Programming Language :: Python :: 3
Classifier: License :: OSI Approved :: MIT License
Classifier: Operating System :: OS Independent
